ex/encoder.v
// Code your design here
module encoder(input wire [3:0] in, output reg [2:0] out);

  always @(in[3], in[2], in[1], in[0])
    begin
      if (in[3] == 1'b1)
        out = 3'b100;
      else if (in[2] == 1'b1)
          out = 3'b011;
      else if (in[1] == 1'b1)
          out = 3'b010;
      else
          out = 3'b001;
    end
endmodule

ex/encoder_bench.v
// test benchmark program on conditionals in the encoder file
module encoder_bench;
  reg [3:0] in;
  wire [2:0] out;

  encoder uut(
    .in(in),
    .out(out)
  );


  initial begin
    $dumpfile("dump.vcd");
    $dumpvars(0, encoder_bench);

    in = 4'b0000;

  #20 in = 4'b0001;
	#20 in = 4'b0010;
	#20 in = 4'b0011;
	#20 in = 4'b0100;
	#20 in = 4'b0101;
	#20 in = 4'b0110;
	#20 in = 4'b0111;
	#20 in = 4'b1000;
	#20 in = 4'b1001;
	#20 in = 4'b1010;
	#20 in = 4'b1011;
	#20 in = 4'b1100;
	#20 in = 4'b1101;
	#20 in = 4'b1110;
	#20 in = 4'b1111;
	#40 ;
  end

  initial begin
	 $monitor("t=%3d in=%4b,out=%3b", $time, in, out);
  end

endmodule

ex/dump.vcd
$date
	Fri Feb 10 22:15:10 2023
$end
$version
	Icarus Verilog
$end
$timescale
	1s
$end
$scope module encoder_bench $end
$var wire 3 ! out [2:0] $end
$var reg 4 " in [3:0] $end
$scope module uut $end
$var wire 4 # in [3:0] $end
$var reg 3 $ out [2:0] $end
$upscope $end
$upscope $end
$enddefinitions $end
#0
$dumpvars
b1 $
b0 #
b0 "
b1 !
$end
#20
b1 "
b1 #
#40
b10 !
b10 $
b10 "
b10 #
#60
b11 "
b11 #
#80
b11 !
b11 $
b100 "
b100 #
#100
b101 "
b101 #
#120
b110 "
b110 #
#140
b111 "
b111 #
#160
b100 !
b100 $
b1000 "
b1000 #
#180
b1001 "
b1001 #
#200
b1010 "
b1010 #
#220
b1011 "
b1011 #
#240
b1100 "
b1100 #
#260
b1101 "
b1101 #
#280
b1110 "
b1110 #
#300
b1111 "
b1111 #
